{
    "playcloud_coder_1": {
        "rx_bytes": 589603,
        "rx_dropped": 0,
        "rx_errors": 0,
        "rx_packets": 148,
        "tx_bytes": 138478,
        "tx_dropped": 0,
        "tx_errors": 0,
        "tx_packets": 117
    },
    "playcloud_metadata_1": {
        "rx_bytes": 11818,
        "rx_dropped": 0,
        "rx_errors": 0,
        "rx_packets": 106,
        "tx_bytes": 19095,
        "tx_dropped": 0,
        "tx_errors": 0,
        "tx_packets": 62
    },
    "playcloud_proxy_1": {
        "rx_bytes": 745630,
        "rx_dropped": 0,
        "rx_errors": 0,
        "rx_packets": 323,
        "tx_bytes": 739685,
        "tx_dropped": 0,
        "tx_errors": 0,
        "tx_packets": 396
    },
    "playcloud_zoo1_1": {
        "rx_bytes": 2191,
        "rx_dropped": 0,
        "rx_errors": 0,
        "rx_packets": 31,
        "tx_bytes": 925,
        "tx_dropped": 0,
        "tx_errors": 0,
        "tx_packets": 12
    },
    "redis": {
        "rx_bytes": 139393,
        "rx_dropped": 0,
        "rx_errors": 0,
        "rx_packets": 159,
        "tx_bytes": 586282,
        "tx_dropped": 0,
        "tx_errors": 0,
        "tx_packets": 121
    }
}
